LICENSE
README.md
setup.py
recruiter_cat/__init__.py
recruiter_cat/base.py
recruiter_cat/contactout.py
recruiter_cat.egg-info/PKG-INFO
recruiter_cat.egg-info/SOURCES.txt
recruiter_cat.egg-info/dependency_links.txt
recruiter_cat.egg-info/requires.txt
recruiter_cat.egg-info/top_level.txt